{
  "openapi": "3.0.0",
  "info": {
    "version": "v0.0.1",
    "title": "Dokumentasi API EVENT",
    "description": "Dokumentasi API EVENT"
  },
  "servers": [
    {
      "url": "http://localhost:3000/api",
      "description": "Local Server"
    },
    {
      "url": "https://back-end-event-five.vercel.app/api",
      "description": "Deploy Server"
    }
  ],
  "paths": {
    "/auth/register": {
      "post": {
        "description": "",
        "responses": {
          "200": {
            "description": "OK"
          },
          "400": {
            "description": "Bad Request"
          }
        },
        "requestBody": {
          "content": {
            "application/json": {
              "schema": {
                "type": "object",
                "properties": {
                  "fullName": {
                    "example": "any"
                  },
                  "username": {
                    "example": "any"
                  },
                  "email": {
                    "example": "any"
                  },
                  "password": {
                    "example": "any"
                  },
                  "confirmPassword": {
                    "example": "any"
                  }
                }
              }
            }
          }
        }
      }
    },
    "/auth/login": {
      "post": {
        "description": "",
        "responses": {
          "200": {
            "description": "OK"
          },
          "400": {
            "description": "Bad Request"
          },
          "403": {
            "description": "Forbidden"
          }
        },
        "requestBody": {
          "required": true,
          "content": {
            "application/json": {
              "schema": {
                "$href": "#/components/schemas/LoginRequest"
              }
            },
            "application/xml": {
              "schema": {
                "$href": "#/components/schemas/LoginRequest"
              }
            }
          }
        }
      }
    },
    "/auth/me": {
      "get": {
        "description": "",
        "responses": {
          "200": {
            "description": "OK"
          },
          "400": {
            "description": "Bad Request"
          },
          "403": {
            "description": "Forbidden"
          }
        },
        "security": [
          {
            "bearerAuth": []
          }
        ]
      }
    }
  },
  "components": {
    "securitySchemes": {
      "bearerAuth": {
        "type": "http",
        "scheme": "bearer"
      }
    },
    "shemas": {
      "LoginRequest": {
        "password": "12341234"
      }
    }
  }
}